elle_numeric-0.0.0-py3.8-nspkg.pth
elle/numeric/__init__.py
elle/numeric/inverse.py
elle/numeric/optimize.py
elle/numeric/path_solve.py
elle_numeric-0.0.0.dist-info/METADATA
elle_numeric-0.0.0.dist-info/WHEEL
elle_numeric-0.0.0.dist-info/namespace_packages.txt
elle_numeric-0.0.0.dist-info/top_level.txt
elle_numeric-0.0.0.dist-info/RECORD
