Metadata-Version: 2.1
Name: elle-numeric
Version: 0.0.0
Summary: Numeric routines.
Home-page: https://github.com/claudioperez/elle-numeric
Author: Claudio Perez
Author-email: claudio_perez@berkeley.edu
License: BSD-3-Clause
Project-URL: Changelog, https://github.com/claudioperez/elle-numeric/blob/master/CHANGELOG.md
Project-URL: Issue Tracker, https://github.com/claudioperez/elle-numeric/issues
Platform: UNKNOWN
Classifier: License :: OSI Approved :: BSD License
Classifier: Operating System :: Unix
Classifier: Operating System :: POSIX
Classifier: Operating System :: Microsoft :: Windows
Classifier: Programming Language :: Python
Classifier: Programming Language :: Python :: 3
Classifier: Programming Language :: Python :: 3.5
Classifier: Programming Language :: Python :: 3.6
Classifier: Programming Language :: Python :: 3.7
Classifier: Programming Language :: Python :: 3.8
Classifier: Programming Language :: Python :: Implementation :: CPython
Classifier: Topic :: Utilities
Requires-Python: !=3.0.*, !=3.1.*, !=3.2.*, !=3.3.*, !=3.4.*
